fletrt/__init__.py
fletrt/navigation_route.py
fletrt/route.py
fletrt/router.py
fletrt/routing_middleware.py
fletrt/templates/__init__.py
fletrt/templates/not_found.py
fletrt/utils/__init__.py
fletrt/utils/navigation_bar_utils.py
fletrt-0.0.4.dist-info/LICENSE
fletrt-0.0.4.dist-info/METADATA
fletrt-0.0.4.dist-info/WHEEL
fletrt-0.0.4.dist-info/RECORD
