Metadata-Version: 2.1
Name: fletrt
Version: 0.0.4
Summary: Simple routing for the Flet framework.
Home-page: https://github.com/pedrog022/fletrt
Keywords: flet,routing
Author: PedroG022
Requires-Python: >=3.7,<4.0
Classifier: Programming Language :: Python :: 3
Classifier: Programming Language :: Python :: 3.7
Classifier: Programming Language :: Python :: 3.8
Classifier: Programming Language :: Python :: 3.9
Classifier: Programming Language :: Python :: 3.10
Classifier: Programming Language :: Python :: 3.11
Classifier: Programming Language :: Python :: 3.12
Requires-Dist: flet (>=0.19.0,<0.20.0)
Project-URL: Repository, https://github.com/pedrog022/fletrt
